smah/__init__.py
smah/args/__init__.py
smah/args/args.py
smah/console/__init__.py
smah/console/console.py
smah/database/__init__.py
smah/database/database.py
smah/database/migration.py
smah/database/migrations/1730153754_history.py
smah/logs/__init__.py
smah/logs/logs.py
smah/runner/__init__.py
smah/runner/prompts.py
smah/runner/response_parser.py
smah/runner/runner.py
smah/settings/.gitignore
smah/settings/__init__.py
smah/settings/configurator.py
smah/settings/inference/__init__.py
smah/settings/inference/configurator.py
smah/settings/inference/inference.py
smah/settings/inference/inference_defaults.yaml
smah/settings/inference/provider/__init__.py
smah/settings/inference/provider/model/__init__.py
smah/settings/inference/provider/model/model.py
smah/settings/inference/provider/provider.py
smah/settings/settings.py
smah/settings/system/__init__.py
smah/settings/system/configurator.py
smah/settings/system/operating_system/__init__.py
smah/settings/system/operating_system/configurator.py
smah/settings/system/operating_system/info/__init__.py
smah/settings/system/operating_system/info/base_info.py
smah/settings/system/operating_system/info/bsd_info.py
smah/settings/system/operating_system/info/darwin_info.py
smah/settings/system/operating_system/info/linux_info.py
smah/settings/system/operating_system/info/windows_info.py
smah/settings/system/operating_system/operating_system.py
smah/settings/system/stats/__init__.py
smah/settings/system/stats/base_stats.py
smah/settings/system/stats/cpu_stats.py
smah/settings/system/stats/disk_stats.py
smah/settings/system/stats/memory_stats.py
smah/settings/system/system.py
smah/settings/user/__init__.py
smah/settings/user/configurator.py
smah/settings/user/user.py
smah/smah.py
smah/smah_migrate.py
smah-0.1.13.dist-info/LICENSE
smah-0.1.13.dist-info/METADATA
smah-0.1.13.dist-info/WHEEL
smah-0.1.13.dist-info/entry_points.txt
smah-0.1.13.dist-info/RECORD
