Metadata-Version: 2.1
Name: smah
Version: 0.1.13
Summary: OpenAI Driven system and user preference aware commandline GPT with pipe processing support and conversation history.
Home-page: https://github.com/noizu-labs-ml/smah
License: MIT
Keywords: openai,command-line,system,automation,smart-pipe
Author: Keith Brings
Author-email: keith.brings@noizu.com
Requires-Python: >=3.10,<4.0
Classifier: Development Status :: 3 - Alpha
Classifier: Intended Audience :: Developers
Classifier: Intended Audience :: System Administrators
Classifier: License :: OSI Approved :: MIT License
Classifier: Programming Language :: Python :: 3
Classifier: Programming Language :: Python :: 3.10
Classifier: Programming Language :: Python :: 3.11
Classifier: Programming Language :: Python :: 3.12
Classifier: Programming Language :: Python :: 3.13
Classifier: Topic :: Software Development :: Libraries :: Python Modules
Classifier: Topic :: System :: Systems Administration
Requires-Dist: aiohttp (>=3.10.10,<4.0.0)
Requires-Dist: cssselect (>=1.2.0,<2.0.0)
Requires-Dist: lxml (>=5.3.0,<6.0.0)
Requires-Dist: openai (>=1.52.0,<2.0.0)
Requires-Dist: prompt-toolkit (>=3.0.48,<4.0.0)
Requires-Dist: psutil (>=6.1.0,<7.0.0)
Requires-Dist: pyyaml (>=6.0.2,<7.0.0)
Requires-Dist: readchar (>=4.2.0,<5.0.0)
Requires-Dist: requests (>=2.32.3,<3.0.0)
Requires-Dist: rich (>=13.9.3,<14.0.0)
Project-URL: Documentation, https://smah.readthedocs.io/en/latest/
Project-URL: Repository, https://github.com/noizu-labs-ml/smah
